drawio2rdf/__init__.py
drawio2rdf/helpers.py
drawio2rdf/analysis/time_analysis.py
drawio2rdf/diagrams/__init__.py
drawio2rdf/diagrams/base.py
drawio2rdf/diagrams/categorization.py
drawio2rdf/diagrams/helpers.py
drawio2rdf/diagrams/rdf_diagram.py
drawio2rdf/diagrams/sql_diagram.py
drawio2rdf/diagrams/typings.py
drawio2rdf/drawio/diagram/__init__.py
drawio2rdf/library/__init__.py
drawio2rdf/library/model/__init__.py
drawio2rdf/library/model/drawio.py
drawio2rdf/library/model/xml_model.py
drawio2rdf/rdf/__init__.py
drawio2rdf-0.0.3.dist-info/LICENCE
drawio2rdf-0.0.3.dist-info/METADATA
drawio2rdf-0.0.3.dist-info/WHEEL
drawio2rdf-0.0.3.dist-info/entry_points.txt
drawio2rdf-0.0.3.dist-info/top_level.txt
drawio2rdf-0.0.3.dist-info/RECORD
